<?xml version="1.0" encoding="UTF-8"?>
<nite:root xmlns:nite="http://nite.sourceforge.net/" id="tok.q1ec3.f">
<tuseq id="q1ec3f.tok.1"><nite:child href="q1ec3.f.timed-units.xml#id(q1ec3f.1)..id(q1ec3f.18)"/></tuseq>
<token turef="q1ec3f.19" estimated="end" end="14.5899" start="14.3577" id="q1ec3f.tok.2">that</token>
<token turef="q1ec3f.19" estimated="start" end="14.5899" start="14.3577" id="q1ec3f.tok.3">+'s</token>
<tuseq id="q1ec3f.tok.4"><nite:child href="q1ec3.f.timed-units.xml#id(q1ec3f.21)..id(q1ec3f.44)"/></tuseq>
<token turef="q1ec3f.45" estimated="end" end="30.0231" start="29.7645" id="q1ec3f.tok.5">have</token>
<token turef="q1ec3f.45" estimated="start" end="30.0231" start="29.7645" id="q1ec3f.tok.6">a</token>
<tuseq id="q1ec3f.tok.7"><nite:child href="q1ec3.f.timed-units.xml#id(q1ec3f.47)..id(q1ec3f.54)"/></tuseq>
<token turef="q1ec3f.55" estimated="end" end="40.7366" start="40.5435" id="q1ec3f.tok.8">is</token>
<token turef="q1ec3f.55" estimated="start" end="40.7366" start="40.5435" id="q1ec3f.tok.9">that</token>
<tuseq id="q1ec3f.tok.10"><nite:child href="q1ec3.f.timed-units.xml#id(q1ec3f.57)..id(q1ec3f.60)"/></tuseq>
<token turef="q1ec3f.62" estimated="end" end="41.7227" start="41.4448" id="q1ec3f.tok.11">that</token>
<token turef="q1ec3f.62" estimated="start" end="41.7227" start="41.4448" id="q1ec3f.tok.12">+'ll</token>
<tuseq id="q1ec3f.tok.13"><nite:child href="q1ec3.f.timed-units.xml#id(q1ec3f.64)..id(q1ec3f.99)"/></tuseq>
<token turef="q1ec3f.100" estimated="end" end="58.7829" start="58.6676" id="q1ec3f.tok.14">i</token>
<token turef="q1ec3f.100" estimated="both" end="58.7829" start="58.6676" id="q1ec3f.tok.15">+'ve</token>
<token turef="q1ec3f.100" estimated="start" end="58.7829" start="58.6676" id="q1ec3f.tok.16">a</token>
<tuseq id="q1ec3f.tok.17"><nite:child href="q1ec3.f.timed-units.xml#id(q1ec3f.103)..id(q1ec3f.132)"/></tuseq>
<token turef="q1ec3f.133" estimated="end" end="73.9674" start="73.7703" id="q1ec3f.tok.18">that</token>
<token turef="q1ec3f.133" estimated="start" end="73.9674" start="73.7703" id="q1ec3f.tok.19">+'s</token>
<tuseq id="q1ec3f.tok.20"><nite:child href="q1ec3.f.timed-units.xml#id(q1ec3f.135)..id(q1ec3f.185)"/></tuseq>
<token turef="q1ec3f.186" estimated="end" end="103.1374" start="103.0386" id="q1ec3f.tok.21">i</token>
<token turef="q1ec3f.186" estimated="start" end="103.1374" start="103.0386" id="q1ec3f.tok.22">+'m</token>
<tuseq id="q1ec3f.tok.23"><nite:child href="q1ec3.f.timed-units.xml#id(q1ec3f.188)..id(q1ec3f.210)"/></tuseq>
<token turef="q1ec3f.211" estimated="end" end="110.9931" start="110.8416" id="q1ec3f.tok.24">i</token>
<token turef="q1ec3f.211" estimated="start" end="110.9931" start="110.8416" id="q1ec3f.tok.25">+'ve</token>
<tuseq id="q1ec3f.tok.26"><nite:child href="q1ec3.f.timed-units.xml#id(q1ec3f.213)..id(q1ec3f.229)"/></tuseq>
<token turef="q1ec3f.230" estimated="end" end="128.9838" start="128.7582" id="q1ec3f.tok.27">can</token>
<token turef="q1ec3f.230" estimated="start" end="128.9838" start="128.7582" id="q1ec3f.tok.28">i</token>
<tuseq id="q1ec3f.tok.29"><nite:child href="q1ec3.f.timed-units.xml#id(q1ec3f.232)..id(q1ec3f.332)"/></tuseq>
<token turef="q1ec3f.333" estimated="end" end="199.3947" start="199.2877" id="q1ec3f.tok.30">i</token>
<token turef="q1ec3f.333" estimated="start" end="199.3947" start="199.2877" id="q1ec3f.tok.31">+'m</token>
<token turef="q1ec3f.335" estimated="end" end="199.5775" start="199.3947" id="q1ec3f.tok.32">that</token>
<token turef="q1ec3f.335" estimated="start" end="199.5775" start="199.3947" id="q1ec3f.tok.33">+'s</token>
<tuseq id="q1ec3f.tok.34"><nite:child href="q1ec3.f.timed-units.xml#id(q1ec3f.337)..id(q1ec3f.354)"/></tuseq>
<token turef="q1ec3f.356" estimated="end" end="205.9291" start="205.7843" id="q1ec3f.tok.35">i</token>
<token turef="q1ec3f.356" estimated="start" end="205.9291" start="205.7843" id="q1ec3f.tok.36">+'m</token>
<tuseq id="q1ec3f.tok.37"><nite:child href="q1ec3.f.timed-units.xml#id(q1ec3f.358)..id(q1ec3f.397)"/></tuseq>
<token turef="q1ec3f.398" estimated="end" end="228.6496" start="228.5396" id="q1ec3f.tok.38">they</token>
<token turef="q1ec3f.398" estimated="start" end="228.6496" start="228.5396" id="q1ec3f.tok.39">+'re</token>
<tuseq id="q1ec3f.tok.40"><nite:child href="q1ec3.f.timed-units.xml#id(q1ec3f.400)..id(q1ec3f.457)"/></tuseq>
<token turef="q1ec3f.458" estimated="end" end="263.0170" start="262.8298" id="q1ec3f.tok.41">i</token>
<token turef="q1ec3f.458" estimated="start" end="263.0170" start="262.8298" id="q1ec3f.tok.42">+'m</token>
<tuseq id="q1ec3f.tok.43"><nite:child href="q1ec3.f.timed-units.xml#id(q1ec3f.460)..id(q1ec3f.471)"/></tuseq>
<token turef="q1ec3f.472" estimated="end" end="267.4131" start="267.1776" id="q1ec3f.tok.44">i</token>
<token turef="q1ec3f.472" estimated="start" end="267.4131" start="267.1776" id="q1ec3f.tok.45">+'m</token>
<tuseq id="q1ec3f.tok.46"><nite:child href="q1ec3.f.timed-units.xml#id(q1ec3f.474)..id(q1ec3f.475)"/></tuseq>
<token turef="q1ec3f.476" estimated="end" end="268.0737" start="267.8940" id="q1ec3f.tok.47">i</token>
<token turef="q1ec3f.476" estimated="start" end="268.0737" start="267.8940" id="q1ec3f.tok.48">+'m</token>
<tuseq id="q1ec3f.tok.49"><nite:child href="q1ec3.f.timed-units.xml#id(q1ec3f.478)..id(q1ec3f.483)"/></tuseq>
<token turef="q1ec3f.484" estimated="end" end="269.9724" start="269.8159" id="q1ec3f.tok.50">i</token>
<token turef="q1ec3f.484" estimated="start" end="269.9724" start="269.8159" id="q1ec3f.tok.51">+'m</token>
<tuseq id="q1ec3f.tok.52"><nite:child href="q1ec3.f.timed-units.xml#id(q1ec3f.486)..id(q1ec3f.516)"/></tuseq>
<token turef="q1ec3f.518" estimated="end" end="277.5827" start="277.5024" id="q1ec3f.tok.53">i</token>
<token turef="q1ec3f.518" estimated="start" end="277.5827" start="277.5024" id="q1ec3f.tok.54">+'ve</token>
<tuseq id="q1ec3f.tok.55"><nite:child href="q1ec3.f.timed-units.xml#id(q1ec3f.520)..id(q1ec3f.534)"/></tuseq>
<token turef="q1ec3f.536" estimated="end" end="283.0849" start="282.9597" id="q1ec3f.tok.56">there</token>
<token turef="q1ec3f.536" estimated="start" end="283.0849" start="282.9597" id="q1ec3f.tok.57">+'s</token>
<tuseq id="q1ec3f.tok.58"><nite:child href="q1ec3.f.timed-units.xml#id(q1ec3f.538)..id(q1ec3f.616)"/></tuseq>
<token turef="q1ec3f.617" estimated="end" end="330.8069" start="330.6771" id="q1ec3f.tok.59">i</token>
<token turef="q1ec3f.617" estimated="start" end="330.8069" start="330.6771" id="q1ec3f.tok.60">+'m</token>
<tuseq id="q1ec3f.tok.61"><nite:child href="q1ec3.f.timed-units.xml#id(q1ec3f.619)..id(q1ec3f.625)"/></tuseq>
<token turef="q1ec3f.626" estimated="end" end="332.0766" start="331.9317" id="q1ec3f.tok.62">i</token>
<token turef="q1ec3f.626" estimated="start" end="332.0766" start="331.9317" id="q1ec3f.tok.63">+'m</token>
<tuseq id="q1ec3f.tok.64"><nite:child href="q1ec3.f.timed-units.xml#id(q1ec3f.628)..id(q1ec3f.656)"/></tuseq>
<token turef="q1ec3f.658" estimated="end" end="340.7048" start="340.5599" id="q1ec3f.tok.65">i</token>
<token turef="q1ec3f.658" estimated="start" end="340.7048" start="340.5599" id="q1ec3f.tok.66">+'m</token>
<tuseq id="q1ec3f.tok.67"><nite:child href="q1ec3.f.timed-units.xml#id(q1ec3f.660)..id(q1ec3f.717)"/></tuseq>
<token turef="q1ec3f.718" estimated="end" end="367.3435" start="367.2315" id="q1ec3f.tok.68">i</token>
<token turef="q1ec3f.718" estimated="start" end="367.3435" start="367.2315" id="q1ec3f.tok.69">+'ve</token>
<tuseq id="q1ec3f.tok.70"><nite:child href="q1ec3.f.timed-units.xml#id(q1ec3f.720)..id(q1ec3f.782)"/></tuseq>
<token turef="q1ec3f.784" estimated="end" end="421.9342" start="421.8420" id="q1ec3f.tok.71">there</token>
<token turef="q1ec3f.784" estimated="start" end="421.9342" start="421.8420" id="q1ec3f.tok.72">+'s</token>
<tuseq id="q1ec3f.tok.73"><nite:child href="q1ec3.f.timed-units.xml#id(q1ec3f.786)..id(q1ec3f.801)"/></tuseq>
<token turef="q1ec3f.802" estimated="end" end="425.7394" start="425.5928" id="q1ec3f.tok.74">i</token>
<token turef="q1ec3f.802" estimated="start" end="425.7394" start="425.5928" id="q1ec3f.tok.75">+'ve</token>
<tuseq id="q1ec3f.tok.76"><nite:child href="q1ec3.f.timed-units.xml#id(q1ec3f.804)..id(q1ec3f.844)"/></tuseq>
<token turef="q1ec3f.845" estimated="end" end="435.3590" start="435.2536" id="q1ec3f.tok.77">i</token>
<token turef="q1ec3f.845" estimated="start" end="435.3590" start="435.2536" id="q1ec3f.tok.78">+'m</token>
<tuseq id="q1ec3f.tok.79"><nite:child href="q1ec3.f.timed-units.xml#id(q1ec3f.847)..id(q1ec3f.921)"/></tuseq>
<token turef="q1ec3f.923" estimated="end" end="479.2094" start="479.0431" id="q1ec3f.tok.80">so</token>
<token turef="q1ec3f.923" estimated="start" end="479.2094" start="479.0431" id="q1ec3f.tok.81">i</token>
<tuseq id="q1ec3f.tok.82"><nite:child href="q1ec3.f.timed-units.xml#id(q1ec3f.925)..id(q1ec3f.934)"/></tuseq>
<token turef="q1ec3f.935" estimated="end" end="487.3780" start="487.3006" id="q1ec3f.tok.83">i</token>
<token turef="q1ec3f.935" estimated="start" end="487.3780" start="487.3006" id="q1ec3f.tok.84">+'m</token>
<tuseq id="q1ec3f.tok.85"><nite:child href="q1ec3.f.timed-units.xml#id(q1ec3f.937)..id(q1ec3f.954)"/></tuseq>
</nite:root>

