<?xml version="1.0" encoding="UTF-8"?>
<nite:root xmlns:nite="http://nite.sourceforge.net/" id="tok.q3nc7.f">
<tuseq id="q3nc7f.tok.1"><nite:child href="q3nc7.f.timed-units.xml#id(q3nc7f.1)..id(q3nc7f.127)"/></tuseq>
<token turef="q3nc7f.128" estimated="end" end="119.9102" start="119.8379" id="q3nc7f.tok.2">i</token>
<token turef="q3nc7f.128" estimated="start" end="119.9102" start="119.8379" id="q3nc7f.tok.3">+'ve</token>
<tuseq id="q3nc7f.tok.4"><nite:child href="q3nc7.f.timed-units.xml#id(q3nc7f.130)..id(q3nc7f.163)"/></tuseq>
<token turef="q3nc7f.164" estimated="end" end="139.2520" start="139.1289" id="q3nc7f.tok.5">i</token>
<token turef="q3nc7f.164" estimated="start" end="139.2520" start="139.1289" id="q3nc7f.tok.6">+'m</token>
<tuseq id="q3nc7f.tok.7"><nite:child href="q3nc7.f.timed-units.xml#id(q3nc7f.166)..id(q3nc7f.191)"/></tuseq>
<token turef="q3nc7f.192" estimated="end" end="148.6709" start="148.5505" id="q3nc7f.tok.8">it</token>
<token turef="q3nc7f.192" estimated="start" end="148.6709" start="148.5505" id="q3nc7f.tok.9">+'s</token>
<tuseq id="q3nc7f.tok.10"><nite:child href="q3nc7.f.timed-units.xml#id(q3nc7f.194)..id(q3nc7f.290)"/></tuseq>
</nite:root>

