<nite:root xmlns:nite="http://nite.sourceforge.net/" id="landmark-refs.q7ec1.g">
<landmark_reference id="q7ec1.g.ref.1" stat="0" lit="l" def="def" men="intro" plural="0" part_reference="no">
  <nite:child href="q7ec1.g.timed-units.xml#id(q7ec1g.19)..id(q7ec1g.20.1)"/>
  <nite:pointer role="landmark" href="maptask-landmarks.xml#id(m14_diamond_mine)"/>
</landmark_reference>
<landmark_reference id="q7ec1.g.ref.2" stat="0" def="pro" men="rep0" lit="none" plural="0" part_reference="no">
  <nite:child href="q7ec1.g.timed-units.xml#id(q7ec1g.34)"/>
  <nite:pointer role="landmark" href="maptask-landmarks.xml#id(m14_diamond_mine)"/>
</landmark_reference>
<landmark_reference id="q7ec1.g.ref.3" stat="0" lit="l" def="def" men="intro" plural="0" part_reference="no">
  <nite:child href="q7ec1.g.timed-units.xml#id(q7ec1g.58)..id(q7ec1g.59)"/>
  <nite:pointer role="landmark" href="maptask-landmarks.xml#id(m14_graveyard)"/>
</landmark_reference>
<landmark_reference id="q7ec1.g.ref.4" stat="0" lit="ld" def="indef" men="rep0" plural="0" part_reference="no">
  <nite:child href="q7ec1.g.timed-units.xml#id(q7ec1g.81)..id(q7ec1g.83)"/>
  <nite:pointer role="landmark" href="maptask-landmarks.xml#id(m14_graveyard)"/>
</landmark_reference>
<landmark_reference id="q7ec1.g.ref.5" stat="0" def="pro" men="rep0" lit="none" plural="0" part_reference="no">
  <nite:child href="q7ec1.g.timed-units.xml#id(q7ec1g.92)"/>
  <nite:pointer role="landmark" href="maptask-landmarks.xml#id(m14_graveyard)"/>
</landmark_reference>
<landmark_reference id="q7ec1.g.ref.6" stat="0" def="pro" men="rep0" lit="none" plural="0" part_reference="no">
  <nite:child href="q7ec1.g.timed-units.xml#id(q7ec1g.94)"/>
  <nite:pointer role="landmark" href="maptask-landmarks.xml#id(m14_graveyard)"/>
</landmark_reference>
<landmark_reference id="q7ec1.g.ref.7" stat="0" lit="l" def="def" men="rep0" plural="0" part_reference="no">
  <nite:child href="q7ec1.g.timed-units.xml#id(q7ec1g.127)..id(q7ec1g.128.1)"/>
  <nite:pointer role="landmark" href="maptask-landmarks.xml#id(m14_diamond_mine)"/>
</landmark_reference>
<landmark_reference id="q7ec1.g.ref.8" stat="0" lit="l" def="def" men="rep0" plural="0" part_reference="no">
  <nite:child href="q7ec1.g.timed-units.xml#id(q7ec1g.147)..id(q7ec1g.148)"/>
  <nite:pointer role="landmark" href="maptask-landmarks.xml#id(m14_graveyard)"/>
</landmark_reference>
<landmark_reference id="q7ec1.g.ref.9" stat="0" lit="l" def="def" men="intro" plural="0" part_reference="no">
  <nite:child href="q7ec1.g.timed-units.xml#id(q7ec1g.225)..id(q7ec1g.227)"/>
  <nite:pointer role="landmark" href="maptask-landmarks.xml#id(m14_carved_stones)"/>
</landmark_reference>
<landmark_reference id="q7ec1.g.ref.10" stat="0" lit="l" def="def" men="intro" plural="0" part_reference="no">
  <nite:child href="q7ec1.g.timed-units.xml#id(q7ec1g.261)..id(q7ec1g.263)"/>
  <nite:pointer role="landmark" href="maptask-landmarks.xml#id(m14_indian_country)"/>
</landmark_reference>
<landmark_reference id="q7ec1.g.ref.11" stat="0" lit="l" def="def" men="rep0" plural="0" part_reference="no">
  <nite:child href="q7ec1.g.timed-units.xml#id(q7ec1g.281)..id(q7ec1g.283)"/>
  <nite:pointer role="landmark" href="maptask-landmarks.xml#id(m14_indian_country)"/>
</landmark_reference>
<landmark_reference id="q7ec1.g.ref.12" stat="0" lit="l" def="def" men="intro" plural="0" part_reference="no">
  <nite:child href="q7ec1.g.timed-units.xml#id(q7ec1g.298)..id(q7ec1g.299.1)"/>
  <nite:pointer role="landmark" href="maptask-landmarks.xml#id(m14_gold_mine)"/>
</landmark_reference>
<landmark_reference id="q7ec1.g.ref.13" stat="0" lit="ld" def="def" men="intro" plural="0" part_reference="no">
  <nite:child href="q7ec1.g.timed-units.xml#id(q7ec1g.318)..id(q7ec1g.322)"/>
  <nite:pointer role="landmark" href="maptask-landmarks.xml#id(m14_great_rock)"/>
</landmark_reference>
<landmark_reference id="q7ec1.g.ref.14" stat="0" lit="l" def="def" men="rep0" plural="0" part_reference="no">
  <nite:child href="q7ec1.g.timed-units.xml#id(q7ec1g.335)..id(q7ec1g.336.1)"/>
  <nite:pointer role="landmark" href="maptask-landmarks.xml#id(m14_gold_mine)"/>
</landmark_reference>
<landmark_reference id="q7ec1.g.ref.15" stat="0" lit="l" def="indef" men="rep0" plural="0" part_reference="no">
  <nite:child href="q7ec1.g.timed-units.xml#id(q7ec1g.350)..id(q7ec1g.351.1)"/>
  <nite:pointer role="landmark" href="maptask-landmarks.xml#id(m14_gold_mine)"/>
</landmark_reference>
<landmark_reference id="q7ec1.g.ref.16" stat="0" lit="l" def="def" men="rep0" plural="0" part_reference="no">
  <nite:child href="q7ec1.g.timed-units.xml#id(q7ec1g.363)..id(q7ec1g.364.1)"/>
  <nite:pointer role="landmark" href="maptask-landmarks.xml#id(m14_gold_mine)"/>
</landmark_reference>
<landmark_reference id="q7ec1.g.ref.17" stat="0" def="pro" men="rep0" lit="none" plural="0" part_reference="no">
  <nite:child href="q7ec1.g.timed-units.xml#id(q7ec1g.387)"/>
  <nite:pointer role="landmark" href="maptask-landmarks.xml#id(m14_gold_mine)"/>
</landmark_reference>
<landmark_reference id="q7ec1.g.ref.18" stat="0" def="pro" men="rep0" lit="none" plural="0" part_reference="no">
  <nite:child href="q7ec1.g.timed-units.xml#id(q7ec1g.403)"/>
  <nite:pointer role="landmark" href="maptask-landmarks.xml#id(m14_gold_mine)"/>
</landmark_reference>
<landmark_reference id="q7ec1.g.ref.19" stat="0" lit="l" def="indef" men="intro_q" plural="0" part_reference="no">
  <nite:child href="q7ec1.g.timed-units.xml#id(q7ec1g.517)..id(q7ec1g.519)"/>
  <nite:pointer role="landmark" href="maptask-landmarks.xml#id(m14_trout_farm)"/>
</landmark_reference>
<landmark_reference id="q7ec1.g.ref.20" stat="0" lit="l" def="def" men="rep0" plural="0" part_reference="no">
  <nite:child href="q7ec1.g.timed-units.xml#id(q7ec1g.534)..id(q7ec1g.536)"/>
  <nite:pointer role="landmark" href="maptask-landmarks.xml#id(m14_trout_farm)"/>
</landmark_reference>
<landmark_reference id="q7ec1.g.ref.21" stat="0" def="pro" men="rep0" lit="none" plural="0" part_reference="no">
  <nite:child href="q7ec1.g.timed-units.xml#id(q7ec1g.547)..id(q7ec1g.552)"/>
  <nite:pointer role="landmark" href="maptask-landmarks.xml#id(m14_trout_farm)"/>
</landmark_reference>
<landmark_reference id="q7ec1.g.ref.22" stat="0" lit="l" def="def" men="intro_q" plural="0" part_reference="no">
  <nite:child href="q7ec1.g.timed-units.xml#id(q7ec1g.554)..id(q7ec1g.555)"/>
  <nite:pointer role="landmark" href="maptask-landmarks.xml#id(m14_cavalry)"/>
</landmark_reference>
<landmark_reference id="q7ec1.g.ref.23" stat="0" def="dctc" men="rep0" lit="none" plural="0" part_reference="no">
  <nite:child href="q7ec1.g.timed-units.xml#id(q7ec1g.569)"/>
  <nite:pointer role="landmark" href="maptask-landmarks.xml#id(m14_cavalry)"/>
</landmark_reference>
<landmark_reference id="q7ec1.g.ref.24" stat="0" lit="nl" def="def" men="rep0" plural="0" part_reference="no">
  <nite:child href="q7ec1.g.timed-units.xml#id(q7ec1g.574)..id(q7ec1g.576)"/>
  <nite:pointer role="landmark" href="maptask-landmarks.xml#id(m14_cavalry)"/>
</landmark_reference>
<landmark_reference id="q7ec1.g.ref.25" stat="0" lit="l" def="null" men="rep0" plural="0" part_reference="no">
  <nite:child href="q7ec1.g.timed-units.xml#id(q7ec1g.590)..id(q7ec1g.591)"/>
  <nite:pointer role="landmark" href="maptask-landmarks.xml#id(m14_trout_farm)"/>
</landmark_reference>
<landmark_reference id="q7ec1.g.ref.26" stat="0" def="pro" men="rep0" lit="none" plural="0" part_reference="no">
  <nite:child href="q7ec1.g.timed-units.xml#id(q7ec1g.608)"/>
  <nite:pointer role="landmark" href="maptask-landmarks.xml#id(m14_trout_farm)"/>
</landmark_reference>
<landmark_reference id="q7ec1.g.ref.27" stat="0" def="pro" men="rep0" lit="none" plural="0" part_reference="no">
  <nite:child href="q7ec1.g.timed-units.xml#id(q7ec1g.629)"/>
  <nite:pointer role="landmark" href="maptask-landmarks.xml#id(m14_trout_farm)"/>
</landmark_reference>
<landmark_reference id="q7ec1.g.ref.28" stat="0" def="pro" men="rep0" lit="none" plural="0" part_reference="no">
  <nite:child href="q7ec1.g.timed-units.xml#id(q7ec1g.661)"/>
  <nite:pointer role="landmark" href="maptask-landmarks.xml#id(m14_trout_farm)"/>
</landmark_reference>
<landmark_reference id="q7ec1.g.ref.29" stat="0" lit="l" def="def" men="rep0" plural="0" part_reference="no">
  <nite:child href="q7ec1.g.timed-units.xml#id(q7ec1g.672)..id(q7ec1g.674)"/>
  <nite:pointer role="landmark" href="maptask-landmarks.xml#id(m14_trout_farm)"/>
</landmark_reference>
<landmark_reference id="q7ec1.g.ref.30" stat="0" lit="l" def="indef" men="intro" plural="0" part_reference="no">
  <nite:child href="q7ec1.g.timed-units.xml#id(q7ec1g.719)..id(q7ec1g.721)"/>
  <nite:pointer role="landmark" href="maptask-landmarks.xml#id(m14_cattle_stockade)"/>
</landmark_reference>
<landmark_reference id="q7ec1.g.ref.31" stat="0" lit="l" def="def" men="rep0" plural="0" part_reference="no">
  <nite:child href="q7ec1.g.timed-units.xml#id(q7ec1g.731)..id(q7ec1g.733)"/>
  <nite:pointer role="landmark" href="maptask-landmarks.xml#id(m14_cattle_stockade)"/>
</landmark_reference>
<landmark_reference id="q7ec1.g.ref.32" stat="0" def="pro" men="rep0" lit="none" plural="0" part_reference="no">
  <nite:child href="q7ec1.g.timed-units.xml#id(q7ec1g.759)"/>
  <nite:pointer role="landmark" href="maptask-landmarks.xml#id(m14_cattle_stockade)"/>
</landmark_reference>
<landmark_reference id="q7ec1.g.ref.33" stat="0" lit="l" def="def" men="intro_q" plural="0" part_reference="no">
  <nite:child href="q7ec1.g.timed-units.xml#id(q7ec1g.771)..id(q7ec1g.773)"/>
  <nite:pointer role="landmark" href="maptask-landmarks.xml#id(m14_bandit_territory)"/>
</landmark_reference>
<landmark_reference id="q7ec1.g.ref.34" stat="0" lit="rl" def="def" men="rep0" plural="0" part_reference="no">
  <nite:child href="q7ec1.g.timed-units.xml#id(q7ec1g.800)..id(q7ec1g.801)"/>
  <nite:pointer role="landmark" href="maptask-landmarks.xml#id(m14_cattle_stockade)"/>
</landmark_reference>
<landmark_reference id="q7ec1.g.ref.35" stat="0" lit="nl" def="def" men="rep0" plural="0" part_reference="no">
  <nite:child href="q7ec1.g.timed-units.xml#id(q7ec1g.821)..id(q7ec1g.824)"/>
  <nite:pointer role="landmark" href="maptask-landmarks.xml#id(m14_parched_river_bed)"/>
</landmark_reference>
<landmark_reference id="q7ec1.g.ref.36" stat="0" lit="l" def="null" men="rep0" plural="0" part_reference="no">
  <nite:child href="q7ec1.g.timed-units.xml#id(q7ec1g.826)..id(q7ec1g.827)"/>
  <nite:pointer role="landmark" href="maptask-landmarks.xml#id(m14_parched_river_bed)"/>
</landmark_reference>
<landmark_reference id="q7ec1.g.ref.37" stat="0" def="dctc" men="rep0" lit="none" plural="0" part_reference="no">
  <nite:child href="q7ec1.g.timed-units.xml#id(q7ec1g.834)"/>
  <nite:pointer role="landmark" href="maptask-landmarks.xml#id(m14_parched_river_bed)"/>
</landmark_reference>
<landmark_reference id="q7ec1.g.ref.38" stat="0" lit="l" def="null" men="rep0" plural="0" part_reference="no">
  <nite:child href="q7ec1.g.timed-units.xml#id(q7ec1g.857)..id(q7ec1g.858)"/>
  <nite:pointer role="landmark" href="maptask-landmarks.xml#id(m14_bandit_territory)"/>
</landmark_reference>
<landmark_reference id="q7ec1.g.ref.39" stat="0" lit="l" def="def" men="intro" plural="0" part_reference="no">
  <nite:child href="q7ec1.g.timed-units.xml#id(q7ec1g.865)..id(q7ec1g.866)"/>
  <nite:pointer role="landmark" href="maptask-landmarks.xml#id(m14_finish)"/>
</landmark_reference>
<landmark_reference id="q7ec1.g.ref.40" stat="0" lit="nl" def="def" men="rep0" plural="0" part_reference="no">
  <nite:child href="q7ec1.g.timed-units.xml#id(q7ec1g.873)..id(q7ec1g.875)"/>
  <nite:pointer role="landmark" href="maptask-landmarks.xml#id(m14_finish)"/>
</landmark_reference>
<landmark_reference id="q7ec1.g.ref.41" stat="0" def="dctc" men="rep0" lit="none" plural="0" part_reference="no">
  <nite:child href="q7ec1.g.timed-units.xml#id(q7ec1g.881)"/>
  <nite:pointer role="landmark" href="maptask-landmarks.xml#id(m14_gallows)"/>
</landmark_reference>
<landmark_reference id="q7ec1.g.ref.42" stat="0" lit="l" def="poss" men="rep0" plural="0" part_reference="no">
  <nite:child href="q7ec1.g.timed-units.xml#id(q7ec1g.882)..id(q7ec1g.883)"/>
  <nite:pointer role="landmark" href="maptask-landmarks.xml#id(m14_finish)"/>
</landmark_reference>
<landmark_reference id="q7ec1.g.ref.43" stat="0" lit="nl" def="indef" men="rep0" plural="0" part_reference="no">
  <nite:child href="q7ec1.g.timed-units.xml#id(q7ec1g.908)..id(q7ec1g.910)"/>
  <nite:pointer role="landmark" href="maptask-landmarks.xml#id(m14_finish)"/>
</landmark_reference>
<landmark_reference id="q7ec1.g.ref.44" stat="0" lit="nl" def="indef" men="rep0" plural="0" part_reference="no">
  <nite:child href="q7ec1.g.timed-units.xml#id(q7ec1g.912)..id(q7ec1g.915)"/>
  <nite:pointer role="landmark" href="maptask-landmarks.xml#id(m14_finish)"/>
</landmark_reference>
<landmark_reference id="q7ec1.g.ref.45" stat="0" lit="l" def="poss" men="rep0" plural="0" part_reference="no">
  <nite:child href="q7ec1.g.timed-units.xml#id(q7ec1g.917)..id(q7ec1g.919)"/>
  <nite:pointer role="landmark" href="maptask-landmarks.xml#id(m14_bandit_territory)"/>
</landmark_reference>
<landmark_reference id="q7ec1.g.ref.46" stat="0" lit="l" def="def" men="rep0" plural="0" part_reference="no">
  <nite:child href="q7ec1.g.timed-units.xml#id(q7ec1g.950)..id(q7ec1g.951.1)"/>
  <nite:pointer role="landmark" href="maptask-landmarks.xml#id(m14_diamond_mine)"/>
</landmark_reference>
<landmark_reference id="q7ec1.g.ref.47" stat="0" lit="l" def="def" men="rep0" plural="0" part_reference="no">
  <nite:child href="q7ec1.g.timed-units.xml#id(q7ec1g.962)..id(q7ec1g.963)"/>
  <nite:pointer role="landmark" href="maptask-landmarks.xml#id(m14_graveyard)"/>
</landmark_reference>
<landmark_reference id="q7ec1.g.ref.48" stat="0" lit="l" def="indef" men="rep0" plural="0" part_reference="no">
  <nite:child href="q7ec1.g.timed-units.xml#id(q7ec1g.971)..id(q7ec1g.972)"/>
  <nite:pointer role="landmark" href="maptask-landmarks.xml#id(m14_graveyard)"/>
</landmark_reference>
<landmark_reference id="q7ec1.g.ref.49" stat="0" lit="l" def="def" men="rep0" plural="0" part_reference="no">
  <nite:child href="q7ec1.g.timed-units.xml#id(q7ec1g.975)..id(q7ec1g.976.1)"/>
  <nite:pointer role="landmark" href="maptask-landmarks.xml#id(m14_diamond_mine)"/>
</landmark_reference>
<landmark_reference id="q7ec1.g.ref.50" stat="0" def="dctc" men="rep0" lit="none" plural="0" part_reference="no">
  <nite:child href="q7ec1.g.timed-units.xml#id(q7ec1g.982)"/>
  <nite:pointer role="landmark" href="maptask-landmarks.xml#id(m14_graveyard)"/>
</landmark_reference>
<landmark_reference id="q7ec1.g.ref.51" stat="0" lit="l" def="def" men="rep0" plural="0" part_reference="no">
  <nite:child href="q7ec1.g.timed-units.xml#id(q7ec1g.994)..id(q7ec1g.995.1)"/>
  <nite:pointer role="landmark" href="maptask-landmarks.xml#id(m14_diamond_mine)"/>
</landmark_reference>
<landmark_reference id="q7ec1.g.ref.52" stat="0" lit="l" def="indef" men="rep0" plural="0" part_reference="no">
  <nite:child href="q7ec1.g.timed-units.xml#id(q7ec1g.1006)..id(q7ec1g.1007)"/>
  <nite:pointer role="landmark" href="maptask-landmarks.xml#id(m14_graveyard)"/>
</landmark_reference>
<landmark_reference id="q7ec1.g.ref.53" stat="0" lit="nl" def="indef" men="rep0" plural="0" part_reference="no">
  <nite:child href="q7ec1.g.timed-units.xml#id(q7ec1g.1023)..id(q7ec1g.1028)"/>
  <nite:pointer role="landmark" href="maptask-landmarks.xml#id(m14_graveyard)"/>
</landmark_reference>
<landmark_reference id="q7ec1.g.ref.54" stat="0" lit="l" def="def" men="rep0" plural="0" part_reference="no">
  <nite:child href="q7ec1.g.timed-units.xml#id(q7ec1g.1039)..id(q7ec1g.1041)"/>
  <nite:pointer role="landmark" href="maptask-landmarks.xml#id(m14_carved_stones)"/>
</landmark_reference>
<landmark_reference id="q7ec1.g.ref.55" stat="0" lit="l" def="null" men="rep0" plural="0" part_reference="no">
  <nite:child href="q7ec1.g.timed-units.xml#id(q7ec1g.1053)..id(q7ec1g.1054)"/>
  <nite:pointer role="landmark" href="maptask-landmarks.xml#id(m14_indian_country)"/>
</landmark_reference>
<landmark_reference id="q7ec1.g.ref.56" stat="0" lit="l" def="indef" men="rep0" plural="0" part_reference="no">
  <nite:child href="q7ec1.g.timed-units.xml#id(q7ec1g.1062)..id(q7ec1g.1064)"/>
  <nite:pointer role="landmark" href="maptask-landmarks.xml#id(m14_great_rock)"/>
</landmark_reference>
<landmark_reference id="q7ec1.g.ref.57" stat="0" lit="l" def="def" men="rep0" plural="0" part_reference="no">
  <nite:child href="q7ec1.g.timed-units.xml#id(q7ec1g.1069)..id(q7ec1g.1072)"/>
  <nite:pointer role="landmark" href="maptask-landmarks.xml#id(m14_indian_country)"/>
</landmark_reference>
<landmark_reference id="q7ec1.g.ref.58" stat="0" lit="l" def="def" men="rep0" plural="0" part_reference="no">
  <nite:child href="q7ec1.g.timed-units.xml#id(q7ec1g.1074)..id(q7ec1g.1075.1)"/>
  <nite:pointer role="landmark" href="maptask-landmarks.xml#id(m14_gold_mine)"/>
</landmark_reference>
<landmark_reference id="q7ec1.g.ref.59" stat="0" lit="l" def="indef" men="rep0" plural="0" part_reference="no">
  <nite:child href="q7ec1.g.timed-units.xml#id(q7ec1g.1084)..id(q7ec1g.1086)"/>
  <nite:pointer role="landmark" href="maptask-landmarks.xml#id(m14_great_rock)"/>
</landmark_reference>
<landmark_reference id="q7ec1.g.ref.60" stat="0" def="pro" men="rep0" lit="none" plural="0" part_reference="no">
  <nite:child href="q7ec1.g.timed-units.xml#id(q7ec1g.1095)"/>
  <nite:pointer role="landmark" href="maptask-landmarks.xml#id(m14_great_rock)"/>
</landmark_reference>
<landmark_reference id="q7ec1.g.ref.61" stat="0" lit="l" def="def" men="rep0" plural="0" part_reference="no">
  <nite:child href="q7ec1.g.timed-units.xml#id(q7ec1g.1103)..id(q7ec1g.1105)"/>
  <nite:pointer role="landmark" href="maptask-landmarks.xml#id(m14_indian_country)"/>
</landmark_reference>
<landmark_reference id="q7ec1.g.ref.62" stat="0" lit="l" def="def" men="rep0" plural="0" part_reference="no">
  <nite:child href="q7ec1.g.timed-units.xml#id(q7ec1g.1112)..id(q7ec1g.1114)"/>
  <nite:pointer role="landmark" href="maptask-landmarks.xml#id(m14_indian_country)"/>
</landmark_reference>
<landmark_reference id="q7ec1.g.ref.63" stat="0" lit="l" def="def" men="rep0" plural="0" part_reference="no">
  <nite:child href="q7ec1.g.timed-units.xml#id(q7ec1g.1116)..id(q7ec1g.1117.1)"/>
  <nite:pointer role="landmark" href="maptask-landmarks.xml#id(m14_gold_mine)"/>
</landmark_reference>
<landmark_reference id="q7ec1.g.ref.64" stat="0" def="pro" men="rep0" lit="none" plural="0" part_reference="no">
  <nite:child href="q7ec1.g.timed-units.xml#id(q7ec1g.1131)"/>
  <nite:pointer role="landmark" href="maptask-landmarks.xml#id(m14_great_rock)"/>
</landmark_reference>
<landmark_reference id="q7ec1.g.ref.65" stat="0" lit="l" def="def" men="rep0" plural="0" part_reference="no">
  <nite:child href="q7ec1.g.timed-units.xml#id(q7ec1g.1137)..id(q7ec1g.1139)"/>
  <nite:pointer role="landmark" href="maptask-landmarks.xml#id(m14_trout_farm)"/>
</landmark_reference>
<landmark_reference id="q7ec1.g.ref.66" stat="0" lit="l" def="def" men="rep0" plural="0" part_reference="no">
  <nite:child href="q7ec1.g.timed-units.xml#id(q7ec1g.1152)..id(q7ec1g.1154)"/>
  <nite:pointer role="landmark" href="maptask-landmarks.xml#id(m14_trout_farm)"/>
</landmark_reference>
<landmark_reference id="q7ec1.g.ref.67" stat="0" lit="nl" def="indef" men="rep0" plural="0" part_reference="no">
  <nite:child href="q7ec1.g.timed-units.xml#id(q7ec1g.1191)..id(q7ec1g.1193)"/>
  <nite:pointer role="landmark" href="maptask-landmarks.xml#id(m14_cavalry)"/>
</landmark_reference>
<landmark_reference id="q7ec1.g.ref.68" stat="0" lit="nl" def="null" men="rep0" plural="0" part_reference="no">
  <nite:child href="q7ec1.g.timed-units.xml#id(q7ec1g.1196)..id(q7ec1g.1197)"/>
  <nite:pointer role="landmark" href="maptask-landmarks.xml#id(m14_cavalry)"/>
</landmark_reference>
<landmark_reference id="q7ec1.g.ref.69" stat="0" def="el" men="rep0" lit="none" plural="0" part_reference="no">
  <nite:child href="q7ec1.g.timed-units.xml#id(q7ec1g.1206)"/>
  <nite:pointer role="landmark" href="maptask-landmarks.xml#id(m14_cavalry)"/>
</landmark_reference>
<landmark_reference id="q7ec1.g.ref.70" stat="0" def="el" men="rep0" lit="none" plural="0" part_reference="no">
  <nite:child href="q7ec1.g.timed-units.xml#id(q7ec1g.1212)"/>
  <nite:pointer role="landmark" href="maptask-landmarks.xml#id(m14_cavalry)"/>
</landmark_reference>
<landmark_reference id="q7ec1.g.ref.71" stat="0" lit="l" def="def" men="rep0" plural="0" part_reference="no">
  <nite:child href="q7ec1.g.timed-units.xml#id(q7ec1g.1213)..id(q7ec1g.1215)"/>
  <nite:pointer role="landmark" href="maptask-landmarks.xml#id(m14_trout_farm)"/>
</landmark_reference>
<landmark_reference id="q7ec1.g.ref.72" stat="0" def="pro" men="rep0" lit="none" plural="0" part_reference="no">
  <nite:child href="q7ec1.g.timed-units.xml#id(q7ec1g.1227)"/>
  <nite:pointer role="landmark" href="maptask-landmarks.xml#id(m14_trout_farm)"/>
</landmark_reference>
<landmark_reference id="q7ec1.g.ref.73" stat="0" lit="rl" def="null" men="rep0" plural="0" part_reference="no">
  <nite:child href="q7ec1.g.timed-units.xml#id(q7ec1g.1243)"/>
  <nite:pointer role="landmark" href="maptask-landmarks.xml#id(m14_cattle_stockade)"/>
</landmark_reference>
<landmark_reference id="q7ec1.g.ref.74" stat="0" def="pro" men="rep0" lit="none" plural="0" part_reference="no">
  <nite:child href="q7ec1.g.timed-units.xml#id(q7ec1g.1247)"/>
  <nite:pointer role="landmark" href="maptask-landmarks.xml#id(m14_cavalry)"/>
</landmark_reference>
<landmark_reference id="q7ec1.g.ref.75" stat="0" lit="l" def="def" plural="1" men="rep0" part_reference="no">
  <nite:child href="q7ec1.g.timed-units.xml#id(q7ec1g.1259)..id(q7ec1g.1261)"/>
  <nite:pointer role="landmark" href="maptask-landmarks.xml#id(m14_cattle_stockade)"/>
</landmark_reference>
<landmark_reference id="q7ec1.g.ref.76" stat="0" lit="l" def="poss" men="rep0" plural="0" part_reference="no">
  <nite:child href="q7ec1.g.timed-units.xml#id(q7ec1g.1271)..id(q7ec1g.1274)"/>
  <nite:pointer role="landmark" href="maptask-landmarks.xml#id(m14_parched_river_bed)"/>
</landmark_reference>
<landmark_reference id="q7ec1.g.ref.77" stat="0" lit="l" def="null" men="rep0" plural="0" part_reference="no">
  <nite:child href="q7ec1.g.timed-units.xml#id(q7ec1g.1283)..id(q7ec1g.1284)"/>
  <nite:pointer role="landmark" href="maptask-landmarks.xml#id(m14_bandit_territory)"/>
</landmark_reference>
<landmark_reference id="q7ec1.g.ref.78" stat="0" lit="nl" def="poss" men="rep0" plural="0" part_reference="no">
  <nite:child href="q7ec1.g.timed-units.xml#id(q7ec1g.1290)..id(q7ec1g.1293)"/>
  <nite:pointer role="landmark" href="maptask-landmarks.xml#id(m14_finish)"/>
</landmark_reference>
<landmark_reference id="q7ec1.g.ref.79" stat="0" lit="l" def="def" men="rep0" plural="0" part_reference="no">
  <nite:child href="q7ec1.g.timed-units.xml#id(q7ec1g.1308)..id(q7ec1g.1310)"/>
  <nite:pointer role="landmark" href="maptask-landmarks.xml#id(m14_bandit_territory)"/>
</landmark_reference>
<landmark_reference id="q7ec1.g.ref.80" stat="0" lit="l" def="def" men="rep0" plural="0" part_reference="no">
  <nite:child href="q7ec1.g.timed-units.xml#id(q7ec1g.1330)..id(q7ec1g.1331)"/>
  <nite:pointer role="landmark" href="maptask-landmarks.xml#id(m14_gallows)"/>
</landmark_reference>
</nite:root>
