<?xml version="1.0" encoding="UTF-8"?>
<nite:root xmlns:nite="http://nite.sourceforge.net/" id="q8ntb1.citations">
<citation id="q8ntb1.cit.1" repetition="1">
  <nite:pointer href="maptask-landmarks.xml#id(m7_crane_bay)" role="landmark"/>
  
    <nite:child href="q8ntb1.wordlist.xml#id(q8ntb1.7)"/>
    <nite:child href="q8ntb1.wordlist.xml#id(q8ntb1.8)"/>
  
</citation>
<citation id="q8ntb1.cit.6" repetition="1">
  <nite:pointer href="maptask-landmarks.xml#id(m10_rock_fall)" role="landmark"/>
  
    <nite:child href="q8ntb1.wordlist.xml#id(q8ntb1.13)"/>
    <nite:child href="q8ntb1.wordlist.xml#id(q8ntb1.14)"/>
  
</citation>
<citation id="q8ntb1.cit.11" repetition="1">
  <nite:pointer href="maptask-landmarks.xml#id(m10_gold_mine)" role="landmark"/>
  
    <nite:child href="q8ntb1.wordlist.xml#id(q8ntb1.18)"/>
    <nite:child href="q8ntb1.wordlist.xml#id(q8ntb1.19)"/>
  
</citation>
<citation id="q8ntb1.cit.16" repetition="1">
  <nite:pointer href="maptask-landmarks.xml#id(m13_collapsed_shelter)" role="landmark"/>
  
    <nite:child href="q8ntb1.wordlist.xml#id(q8ntb1.23)"/>
    <nite:child href="q8ntb1.wordlist.xml#id(q8ntb1.24)"/>
  
</citation>
<citation id="q8ntb1.cit.21" repetition="1">
  <nite:pointer href="maptask-landmarks.xml#id(m10_crocodiles)" role="landmark"/>
  
    <nite:child href="q8ntb1.wordlist.xml#id(q8ntb1.27)"/>
  
</citation>
<citation id="q8ntb1.cit.25" repetition="1">
  <nite:pointer href="maptask-landmarks.xml#id(m10_diamond_mine)" role="landmark"/>
  
    <nite:child href="q8ntb1.wordlist.xml#id(q8ntb1.35)"/>
    <nite:child href="q8ntb1.wordlist.xml#id(q8ntb1.36)"/>
  
</citation>
<citation id="q8ntb1.cit.30" repetition="1">
  <nite:pointer href="maptask-landmarks.xml#id(m0_west_lake)" role="landmark"/>
  
    <nite:child href="q8ntb1.wordlist.xml#id(q8ntb1.38)"/>
    <nite:child href="q8ntb1.wordlist.xml#id(q8ntb1.39)"/>
  
</citation>
<citation id="q8ntb1.cit.35" repetition="1">
  <nite:pointer href="maptask-landmarks.xml#id(m10_disused_warehouse)" role="landmark"/>
  
    <nite:child href="q8ntb1.wordlist.xml#id(q8ntb1.43)"/>
    <nite:child href="q8ntb1.wordlist.xml#id(q8ntb1.44)"/>
  
</citation>
<citation id="q8ntb1.cit.40" repetition="1">
  <nite:pointer href="maptask-landmarks.xml#id(m0_disused_monastery)" role="landmark"/>
  
    <nite:child href="q8ntb1.wordlist.xml#id(q8ntb1.52)"/>
    <nite:child href="q8ntb1.wordlist.xml#id(q8ntb1.53)"/>
  
</citation>
<citation id="q8ntb1.cit.45" repetition="1">
  <nite:pointer href="maptask-landmarks.xml#id(m7_carpenters_cottage)" role="landmark"/>
  
    <nite:child href="q8ntb1.wordlist.xml#id(q8ntb1.58)"/>
    <nite:child href="q8ntb1.wordlist.xml#id(q8ntb1.59)"/>
  
</citation>
<citation id="q8ntb1.cit.50" repetition="1">
  <nite:pointer href="maptask-landmarks.xml#id(m10_highest_viewpoint)" role="landmark"/>
  
    <nite:child href="q8ntb1.wordlist.xml#id(q8ntb1.63)"/>
    <nite:child href="q8ntb1.wordlist.xml#id(q8ntb1.64)"/>
  
</citation>
<citation id="q8ntb1.cit.55" repetition="1">
  <nite:pointer href="maptask-landmarks.xml#id(m13_tribal_settlement)" role="landmark"/>
  
    <nite:child href="q8ntb1.wordlist.xml#id(q8ntb1.66)"/>
    <nite:child href="q8ntb1.wordlist.xml#id(q8ntb1.67)"/>
  
</citation>
<citation id="q8ntb1.cit.60" repetition="1">
  <nite:pointer href="maptask-landmarks.xml#id(m7_burnt_forest)" role="landmark"/>
  
    <nite:child href="q8ntb1.wordlist.xml#id(q8ntb1.69)"/>
    <nite:child href="q8ntb1.wordlist.xml#id(q8ntb1.70)"/>
  
</citation>
<citation id="q8ntb1.cit.65" repetition="1">
  <nite:pointer href="maptask-landmarks.xml#id(m10_rope_bridge)" role="landmark"/>
  <nite:pointer href="maptask-landmarks.xml#id(m13_rope_bridge)" role="landmark"/>
  
    <nite:child href="q8ntb1.wordlist.xml#id(q8ntb1.76)"/>
    <nite:child href="q8ntb1.wordlist.xml#id(q8ntb1.77)"/>
  
</citation>
<citation id="q8ntb1.cit.71" repetition="1">
  <nite:pointer href="maptask-landmarks.xml#id(m0_picket_fence)" role="landmark"/>
  
    <nite:child href="q8ntb1.wordlist.xml#id(q8ntb1.80)"/>
    <nite:child href="q8ntb1.wordlist.xml#id(q8ntb1.81)"/>
  
</citation>
<citation id="q8ntb1.cit.76" repetition="1">
  <nite:pointer href="maptask-landmarks.xml#id(m0_parked_van)" role="landmark"/>
  
    <nite:child href="q8ntb1.wordlist.xml#id(q8ntb1.83)"/>
    <nite:child href="q8ntb1.wordlist.xml#id(q8ntb1.84)"/>
  
</citation>
<citation id="q8ntb1.cit.81" repetition="1">
  <nite:pointer href="maptask-landmarks.xml#id(m7_avalanche)" role="landmark"/>
  
    <nite:child href="q8ntb1.wordlist.xml#id(q8ntb1.94)"/>
  
</citation>
<citation id="q8ntb1.cit.85" repetition="1">
  <nite:pointer href="maptask-landmarks.xml#id(m13_golden_beach)" role="landmark"/>
  
    <nite:child href="q8ntb1.wordlist.xml#id(q8ntb1.98)"/>
    <nite:child href="q8ntb1.wordlist.xml#id(q8ntb1.99)"/>
  
</citation>
<citation id="q8ntb1.cit.90" repetition="1">
  <nite:pointer href="maptask-landmarks.xml#id(m7_tilled_land)" role="landmark"/>
  
    <nite:child href="q8ntb1.wordlist.xml#id(q8ntb1.104)"/>
    <nite:child href="q8ntb1.wordlist.xml#id(q8ntb1.105)"/>
  
</citation>
<citation id="q8ntb1.cit.95" repetition="1">
  <nite:pointer href="maptask-landmarks.xml#id(m10_springboks)" role="landmark"/>
  
    <nite:child href="q8ntb1.wordlist.xml#id(q8ntb1.110)"/>
  
</citation>
<citation id="q8ntb1.cit.99" repetition="1">
  <nite:pointer href="maptask-landmarks.xml#id(m0_yacht_club)" role="landmark"/>
  
    <nite:child href="q8ntb1.wordlist.xml#id(q8ntb1.116)"/>
    <nite:child href="q8ntb1.wordlist.xml#id(q8ntb1.117)"/>
  
</citation>
<citation id="q8ntb1.cit.104" repetition="1">
  <nite:pointer href="maptask-landmarks.xml#id(m10_overgrown_gully)" role="landmark"/>
  
    <nite:child href="q8ntb1.wordlist.xml#id(q8ntb1.119)"/>
    <nite:child href="q8ntb1.wordlist.xml#id(q8ntb1.120)"/>
  
</citation>
<citation id="q8ntb1.cit.109" repetition="1">
  <nite:pointer href="maptask-landmarks.xml#id(m13_secret_valley)" role="landmark"/>
  
    <nite:child href="q8ntb1.wordlist.xml#id(q8ntb1.123)"/>
    <nite:child href="q8ntb1.wordlist.xml#id(q8ntb1.124)"/>
  
</citation>
<citation id="q8ntb1.cit.114" repetition="1">
  <nite:pointer href="maptask-landmarks.xml#id(m0_level_crossing)" role="landmark"/>
  
    <nite:child href="q8ntb1.wordlist.xml#id(q8ntb1.129)"/>
    <nite:child href="q8ntb1.wordlist.xml#id(q8ntb1.130)"/>
  
</citation>
<citation id="q8ntb1.cit.119" repetition="1">
  <nite:pointer href="maptask-landmarks.xml#id(m13_white_mountain)" role="landmark"/>
  
    <nite:child href="q8ntb1.wordlist.xml#id(q8ntb1.133)"/>
    <nite:child href="q8ntb1.wordlist.xml#id(q8ntb1.134)"/>
  
</citation>
<citation id="q8ntb1.cit.124" repetition="1">
  <nite:pointer href="maptask-landmarks.xml#id(m0_alpine_garden)" role="landmark"/>
  
    <nite:child href="q8ntb1.wordlist.xml#id(q8ntb1.136)"/>
    <nite:child href="q8ntb1.wordlist.xml#id(q8ntb1.137)"/>
  
</citation>
<citation id="q8ntb1.cit.129" repetition="1">
  <nite:pointer href="maptask-landmarks.xml#id(m0_flight_museum)" role="landmark"/>
  
    <nite:child href="q8ntb1.wordlist.xml#id(q8ntb1.140)"/>
    <nite:child href="q8ntb1.wordlist.xml#id(q8ntb1.141)"/>
  
</citation>
<citation id="q8ntb1.cit.134" repetition="1">
  <nite:pointer href="maptask-landmarks.xml#id(m10_banana_tree)" role="landmark"/>
  
    <nite:child href="q8ntb1.wordlist.xml#id(q8ntb1.148)"/>
    <nite:child href="q8ntb1.wordlist.xml#id(q8ntb1.149)"/>
  
</citation>
<citation id="q8ntb1.cit.139" repetition="1">
  <nite:pointer href="maptask-landmarks.xml#id(m0_youth_hostel)" role="landmark"/>
  
    <nite:child href="q8ntb1.wordlist.xml#id(q8ntb1.153)"/>
    <nite:child href="q8ntb1.wordlist.xml#id(q8ntb1.154)"/>
  
</citation>
<citation id="q8ntb1.cit.144" repetition="1">
  <nite:pointer href="maptask-landmarks.xml#id(m0_camera_shop)" role="landmark"/>
  
    <nite:child href="q8ntb1.wordlist.xml#id(q8ntb1.158)"/>
    <nite:child href="q8ntb1.wordlist.xml#id(q8ntb1.159)"/>
  
</citation>
<citation id="q8ntb1.cit.149" repetition="1">
  <nite:pointer href="maptask-landmarks.xml#id(m10_field_station)" role="landmark"/>
  
    <nite:child href="q8ntb1.wordlist.xml#id(q8ntb1.161)"/>
    <nite:child href="q8ntb1.wordlist.xml#id(q8ntb1.162)"/>
  
</citation>
<citation id="q8ntb1.cit.154" repetition="1">
  <nite:pointer href="maptask-landmarks.xml#id(m13_pelicans)" role="landmark"/>
  
    <nite:child href="q8ntb1.wordlist.xml#id(q8ntb1.166)"/>
  
</citation>
<citation id="q8ntb1.cit.158" repetition="1">
  <nite:pointer href="maptask-landmarks.xml#id(m7_concealed_hideout)" role="landmark"/>
  
    <nite:child href="q8ntb1.wordlist.xml#id(q8ntb1.170)"/>
    <nite:child href="q8ntb1.wordlist.xml#id(q8ntb1.171)"/>
  
</citation>
<citation id="q8ntb1.cit.163" repetition="1">
  <nite:pointer href="maptask-landmarks.xml#id(m7_remote_village)" role="landmark"/>
  
    <nite:child href="q8ntb1.wordlist.xml#id(q8ntb1.173)"/>
    <nite:child href="q8ntb1.wordlist.xml#id(q8ntb1.174)"/>
  
</citation>
<citation id="q8ntb1.cit.168" repetition="1">
  <nite:pointer href="maptask-landmarks.xml#id(m10_giraffes)" role="landmark"/>
  
    <nite:child href="q8ntb1.wordlist.xml#id(q8ntb1.179)"/>
  
</citation>
<citation id="q8ntb1.cit.172" repetition="1">
  <nite:pointer href="maptask-landmarks.xml#id(m0_thatched_mud_hut)" role="landmark"/>
  
    <nite:child href="q8ntb1.wordlist.xml#id(q8ntb1.184)"/>
    <nite:child href="q8ntb1.wordlist.xml#id(q8ntb1.185)"/>
    <nite:child href="q8ntb1.wordlist.xml#id(q8ntb1.186)"/>
  
</citation>
<citation id="q8ntb1.cit.178" repetition="1">
  <nite:pointer href="maptask-landmarks.xml#id(m10_great_lake)" role="landmark"/>
  
    <nite:child href="q8ntb1.wordlist.xml#id(q8ntb1.190)"/>
    <nite:child href="q8ntb1.wordlist.xml#id(q8ntb1.191)"/>
  
</citation>
<citation id="q8ntb1.cit.183" repetition="1">
  <nite:pointer href="maptask-landmarks.xml#id(m13_crevasse)" role="landmark"/>
  
    <nite:child href="q8ntb1.wordlist.xml#id(q8ntb1.193)"/>
  
</citation>
<citation id="q8ntb1.cit.187" repetition="1">
  <nite:pointer href="maptask-landmarks.xml#id(m13_submerged_rocks)" role="landmark"/>
  
    <nite:child href="q8ntb1.wordlist.xml#id(q8ntb1.195)"/>
    <nite:child href="q8ntb1.wordlist.xml#id(q8ntb1.196)"/>
  
</citation>
<citation id="q8ntb1.cit.192" repetition="1">
  <nite:pointer href="maptask-landmarks.xml#id(m10_safari_truck)" role="landmark"/>
  
    <nite:child href="q8ntb1.wordlist.xml#id(q8ntb1.200)"/>
    <nite:child href="q8ntb1.wordlist.xml#id(q8ntb1.201)"/>
  
</citation>
<citation id="q8ntb1.cit.197" repetition="1">
  <nite:pointer href="maptask-landmarks.xml#id(m13_saxon_barn)" role="landmark"/>
  
    <nite:child href="q8ntb1.wordlist.xml#id(q8ntb1.203)"/>
    <nite:child href="q8ntb1.wordlist.xml#id(q8ntb1.204)"/>
  
</citation>
<citation id="q8ntb1.cit.202" repetition="1">
  <nite:pointer href="maptask-landmarks.xml#id(m7_flagship)" role="landmark"/>
  
    <nite:child href="q8ntb1.wordlist.xml#id(q8ntb1.206)"/>
  
</citation>
<citation id="q8ntb1.cit.206" repetition="1">
  <nite:pointer href="maptask-landmarks.xml#id(m7_coconut_palm)" role="landmark"/>
  
    <nite:child href="q8ntb1.wordlist.xml#id(q8ntb1.210)"/>
    <nite:child href="q8ntb1.wordlist.xml#id(q8ntb1.211)"/>
  
</citation>
<citation id="q8ntb1.cit.211" repetition="1">
  <nite:pointer href="maptask-landmarks.xml#id(m13_slate_mountain)" role="landmark"/>
  
    <nite:child href="q8ntb1.wordlist.xml#id(q8ntb1.213)"/>
    <nite:child href="q8ntb1.wordlist.xml#id(q8ntb1.214)"/>
  
</citation>
<citation id="q8ntb1.cit.216" repetition="1">
  <nite:pointer href="maptask-landmarks.xml#id(m7_ravine)" role="landmark"/>
  
    <nite:child href="q8ntb1.wordlist.xml#id(q8ntb1.218)"/>
  
</citation>
<citation id="q8ntb1.cit.220" repetition="1">
  <nite:pointer href="maptask-landmarks.xml#id(m7_pebbled_shore)" role="landmark"/>
  
    <nite:child href="q8ntb1.wordlist.xml#id(q8ntb1.221)"/>
    <nite:child href="q8ntb1.wordlist.xml#id(q8ntb1.222)"/>
  
</citation>
<citation id="q8ntb1.cit.225" repetition="1">
  <nite:pointer href="maptask-landmarks.xml#id(m7_boat_house)" role="landmark"/>
  
    <nite:child href="q8ntb1.wordlist.xml#id(q8ntb1.224)"/>
    <nite:child href="q8ntb1.wordlist.xml#id(q8ntb1.225)"/>
  
</citation>
<citation id="q8ntb1.cit.230" repetition="1">
  <nite:pointer href="maptask-landmarks.xml#id(m0_allotments)" role="landmark"/>
  
    <nite:child href="q8ntb1.wordlist.xml#id(q8ntb1.227)"/>
  
</citation>
<citation id="q8ntb1.cit.234" repetition="1">
  <nite:pointer href="maptask-landmarks.xml#id(m7_washed_stones)" role="landmark"/>
  
    <nite:child href="q8ntb1.wordlist.xml#id(q8ntb1.231)"/>
    <nite:child href="q8ntb1.wordlist.xml#id(q8ntb1.232)"/>
  
</citation>
<citation id="q8ntb1.cit.239" repetition="1">
  <nite:pointer href="maptask-landmarks.xml#id(m0_telephone_box)" role="landmark"/>
  
    <nite:child href="q8ntb1.wordlist.xml#id(q8ntb1.237)"/>
    <nite:child href="q8ntb1.wordlist.xml#id(q8ntb1.238)"/>
  
</citation>
<citation id="q8ntb1.cit.244" repetition="1">
  <nite:pointer href="maptask-landmarks.xml#id(m13_machete)" role="landmark"/>
  
    <nite:child href="q8ntb1.wordlist.xml#id(q8ntb1.242)"/>
  
</citation>
<citation id="q8ntb1.cit.248" repetition="1">
  <nite:pointer href="maptask-landmarks.xml#id(m7_pine_grove)" role="landmark"/>
  
    <nite:child href="q8ntb1.wordlist.xml#id(q8ntb1.246)"/>
    <nite:child href="q8ntb1.wordlist.xml#id(q8ntb1.247)"/>
  
</citation>
<citation id="q8ntb1.cit.253" repetition="2">
  <nite:pointer href="maptask-landmarks.xml#id(m10_safari_truck)" role="landmark"/>
  
    <nite:child href="q8ntb1.wordlist.xml#id(q8ntb1.249)"/>
    <nite:child href="q8ntb1.wordlist.xml#id(q8ntb1.250)"/>
  
</citation>
<citation id="q8ntb1.cit.258" repetition="2">
  <nite:pointer href="maptask-landmarks.xml#id(m10_highest_viewpoint)" role="landmark"/>
  
    <nite:child href="q8ntb1.wordlist.xml#id(q8ntb1.255)"/>
    <nite:child href="q8ntb1.wordlist.xml#id(q8ntb1.256)"/>
  
</citation>
<citation id="q8ntb1.cit.263" repetition="2">
  <nite:pointer href="maptask-landmarks.xml#id(m10_giraffes)" role="landmark"/>
  
    <nite:child href="q8ntb1.wordlist.xml#id(q8ntb1.258)"/>
  
</citation>
<citation id="q8ntb1.cit.267" repetition="2">
  <nite:pointer href="maptask-landmarks.xml#id(m0_flight_museum)" role="landmark"/>
  
    <nite:child href="q8ntb1.wordlist.xml#id(q8ntb1.267)"/>
    <nite:child href="q8ntb1.wordlist.xml#id(q8ntb1.268)"/>
  
</citation>
<citation id="q8ntb1.cit.272" repetition="2">
  <nite:pointer href="maptask-landmarks.xml#id(m10_banana_tree)" role="landmark"/>
  
    <nite:child href="q8ntb1.wordlist.xml#id(q8ntb1.270)"/>
    <nite:child href="q8ntb1.wordlist.xml#id(q8ntb1.271)"/>
  
</citation>
<citation id="q8ntb1.cit.277" repetition="2">
  <nite:pointer href="maptask-landmarks.xml#id(m13_tribal_settlement)" role="landmark"/>
  
    <nite:child href="q8ntb1.wordlist.xml#id(q8ntb1.275)"/>
    <nite:child href="q8ntb1.wordlist.xml#id(q8ntb1.276)"/>
  
</citation>
<citation id="q8ntb1.cit.282" repetition="2">
  <nite:pointer href="maptask-landmarks.xml#id(m7_coconut_palm)" role="landmark"/>
  
    <nite:child href="q8ntb1.wordlist.xml#id(q8ntb1.278)"/>
    <nite:child href="q8ntb1.wordlist.xml#id(q8ntb1.279)"/>
  
</citation>
<citation id="q8ntb1.cit.287" repetition="2">
  <nite:pointer href="maptask-landmarks.xml#id(m7_crane_bay)" role="landmark"/>
  
    <nite:child href="q8ntb1.wordlist.xml#id(q8ntb1.283)"/>
    <nite:child href="q8ntb1.wordlist.xml#id(q8ntb1.284)"/>
  
</citation>
<citation id="q8ntb1.cit.292" repetition="2">
  <nite:pointer href="maptask-landmarks.xml#id(m10_disused_warehouse)" role="landmark"/>
  
    <nite:child href="q8ntb1.wordlist.xml#id(q8ntb1.289)"/>
    <nite:child href="q8ntb1.wordlist.xml#id(q8ntb1.290)"/>
  
</citation>
<citation id="q8ntb1.cit.297" repetition="2">
  <nite:pointer href="maptask-landmarks.xml#id(m7_boat_house)" role="landmark"/>
  
    <nite:child href="q8ntb1.wordlist.xml#id(q8ntb1.292)"/>
    <nite:child href="q8ntb1.wordlist.xml#id(q8ntb1.293)"/>
  
</citation>
<citation id="q8ntb1.cit.302" repetition="2">
  <nite:pointer href="maptask-landmarks.xml#id(m10_diamond_mine)" role="landmark"/>
  
    <nite:child href="q8ntb1.wordlist.xml#id(q8ntb1.295)"/>
    <nite:child href="q8ntb1.wordlist.xml#id(q8ntb1.296)"/>
  
</citation>
<citation id="q8ntb1.cit.307" repetition="2">
  <nite:pointer href="maptask-landmarks.xml#id(m0_yacht_club)" role="landmark"/>
  
    <nite:child href="q8ntb1.wordlist.xml#id(q8ntb1.299)"/>
    <nite:child href="q8ntb1.wordlist.xml#id(q8ntb1.300)"/>
  
</citation>
<citation id="q8ntb1.cit.312" repetition="2">
  <nite:pointer href="maptask-landmarks.xml#id(m10_rock_fall)" role="landmark"/>
  
    <nite:child href="q8ntb1.wordlist.xml#id(q8ntb1.306)"/>
    <nite:child href="q8ntb1.wordlist.xml#id(q8ntb1.307)"/>
  
</citation>
<citation id="q8ntb1.cit.317" repetition="2">
  <nite:pointer href="maptask-landmarks.xml#id(m7_carpenters_cottage)" role="landmark"/>
  
    <nite:child href="q8ntb1.wordlist.xml#id(q8ntb1.318)"/>
    <nite:child href="q8ntb1.wordlist.xml#id(q8ntb1.319)"/>
  
</citation>
<citation id="q8ntb1.cit.322" repetition="2">
  <nite:pointer href="maptask-landmarks.xml#id(m0_allotments)" role="landmark"/>
  
    <nite:child href="q8ntb1.wordlist.xml#id(q8ntb1.323)"/>
  
</citation>
<citation id="q8ntb1.cit.326" repetition="2">
  <nite:pointer href="maptask-landmarks.xml#id(m7_concealed_hideout)" role="landmark"/>
  
    <nite:child href="q8ntb1.wordlist.xml#id(q8ntb1.325)"/>
    <nite:child href="q8ntb1.wordlist.xml#id(q8ntb1.326)"/>
  
</citation>
<citation id="q8ntb1.cit.331" repetition="2">
  <nite:pointer href="maptask-landmarks.xml#id(m10_overgrown_gully)" role="landmark"/>
  
    <nite:child href="q8ntb1.wordlist.xml#id(q8ntb1.328)"/>
    <nite:child href="q8ntb1.wordlist.xml#id(q8ntb1.329)"/>
  
</citation>
<citation id="q8ntb1.cit.336" repetition="2">
  <nite:pointer href="maptask-landmarks.xml#id(m7_avalanche)" role="landmark"/>
  
    <nite:child href="q8ntb1.wordlist.xml#id(q8ntb1.332)"/>
  
</citation>
<citation id="q8ntb1.cit.340" repetition="2">
  <nite:pointer href="maptask-landmarks.xml#id(m7_remote_village)" role="landmark"/>
  
    <nite:child href="q8ntb1.wordlist.xml#id(q8ntb1.336)"/>
    <nite:child href="q8ntb1.wordlist.xml#id(q8ntb1.337)"/>
  
</citation>
<citation id="q8ntb1.cit.345" repetition="2">
  <nite:pointer href="maptask-landmarks.xml#id(m13_saxon_barn)" role="landmark"/>
  
    <nite:child href="q8ntb1.wordlist.xml#id(q8ntb1.339)"/>
    <nite:child href="q8ntb1.wordlist.xml#id(q8ntb1.340)"/>
  
</citation>
<citation id="q8ntb1.cit.350" repetition="2">
  <nite:pointer href="maptask-landmarks.xml#id(m7_ravine)" role="landmark"/>
  
    <nite:child href="q8ntb1.wordlist.xml#id(q8ntb1.345)"/>
  
</citation>
<citation id="q8ntb1.cit.354" repetition="1">
  <nite:pointer href="maptask-landmarks.xml#id(m0_east_lake)" role="landmark"/>
  
    <nite:child href="q8ntb1.wordlist.xml#id(q8ntb1.350)"/>
    <nite:child href="q8ntb1.wordlist.xml#id(q8ntb1.351)"/>
  
</citation>
<citation id="q8ntb1.cit.359" repetition="2">
  <nite:pointer href="maptask-landmarks.xml#id(m13_golden_beach)" role="landmark"/>
  
    <nite:child href="q8ntb1.wordlist.xml#id(q8ntb1.353)"/>
    <nite:child href="q8ntb1.wordlist.xml#id(q8ntb1.354)"/>
  
</citation>
<citation id="q8ntb1.cit.364" repetition="2">
  <nite:pointer href="maptask-landmarks.xml#id(m7_pine_grove)" role="landmark"/>
  
    <nite:child href="q8ntb1.wordlist.xml#id(q8ntb1.356)"/>
    <nite:child href="q8ntb1.wordlist.xml#id(q8ntb1.357)"/>
  
</citation>
<citation id="q8ntb1.cit.369" repetition="2">
  <nite:pointer href="maptask-landmarks.xml#id(m0_telephone_box)" role="landmark"/>
  
    <nite:child href="q8ntb1.wordlist.xml#id(q8ntb1.359)"/>
    <nite:child href="q8ntb1.wordlist.xml#id(q8ntb1.360)"/>
  
</citation>
<citation id="q8ntb1.cit.374" repetition="2">
  <nite:pointer href="maptask-landmarks.xml#id(m0_picket_fence)" role="landmark"/>
  
    <nite:child href="q8ntb1.wordlist.xml#id(q8ntb1.362)"/>
    <nite:child href="q8ntb1.wordlist.xml#id(q8ntb1.363)"/>
  
</citation>
<citation id="q8ntb1.cit.379" repetition="2">
  <nite:pointer href="maptask-landmarks.xml#id(m7_burnt_forest)" role="landmark"/>
  
    <nite:child href="q8ntb1.wordlist.xml#id(q8ntb1.367)"/>
    <nite:child href="q8ntb1.wordlist.xml#id(q8ntb1.368)"/>
  
</citation>
<citation id="q8ntb1.cit.384" repetition="2">
  <nite:pointer href="maptask-landmarks.xml#id(m0_parked_van)" role="landmark"/>
  
    <nite:child href="q8ntb1.wordlist.xml#id(q8ntb1.374)"/>
    <nite:child href="q8ntb1.wordlist.xml#id(q8ntb1.375)"/>
  
</citation>
<citation id="q8ntb1.cit.389" repetition="2">
  <nite:pointer href="maptask-landmarks.xml#id(m7_tilled_land)" role="landmark"/>
  
    <nite:child href="q8ntb1.wordlist.xml#id(q8ntb1.379)"/>
    <nite:child href="q8ntb1.wordlist.xml#id(q8ntb1.380)"/>
  
</citation>
<citation id="q8ntb1.cit.394" repetition="2">
  <nite:pointer href="maptask-landmarks.xml#id(m7_pebbled_shore)" role="landmark"/>
  
    <nite:child href="q8ntb1.wordlist.xml#id(q8ntb1.382)"/>
    <nite:child href="q8ntb1.wordlist.xml#id(q8ntb1.383)"/>
  
</citation>
<citation id="q8ntb1.cit.399" repetition="2">
  <nite:pointer href="maptask-landmarks.xml#id(m10_field_station)" role="landmark"/>
  
    <nite:child href="q8ntb1.wordlist.xml#id(q8ntb1.387)"/>
    <nite:child href="q8ntb1.wordlist.xml#id(q8ntb1.388)"/>
  
</citation>
<citation id="q8ntb1.cit.404" repetition="2">
  <nite:pointer href="maptask-landmarks.xml#id(m0_level_crossing)" role="landmark"/>
  
    <nite:child href="q8ntb1.wordlist.xml#id(q8ntb1.390)"/>
    <nite:child href="q8ntb1.wordlist.xml#id(q8ntb1.391)"/>
  
</citation>
<citation id="q8ntb1.cit.409" repetition="2">
  <nite:pointer href="maptask-landmarks.xml#id(m13_machete)" role="landmark"/>
  
    <nite:child href="q8ntb1.wordlist.xml#id(q8ntb1.395)"/>
  
</citation>
<citation id="q8ntb1.cit.413" repetition="2">
  <nite:pointer href="maptask-landmarks.xml#id(m13_white_mountain)" role="landmark"/>
  
    <nite:child href="q8ntb1.wordlist.xml#id(q8ntb1.399)"/>
    <nite:child href="q8ntb1.wordlist.xml#id(q8ntb1.400)"/>
  
</citation>
<citation id="q8ntb1.cit.418" repetition="2">
  <nite:pointer href="maptask-landmarks.xml#id(m0_youth_hostel)" role="landmark"/>
  
    <nite:child href="q8ntb1.wordlist.xml#id(q8ntb1.404)"/>
    <nite:child href="q8ntb1.wordlist.xml#id(q8ntb1.405)"/>
  
</citation>
<citation id="q8ntb1.cit.423" repetition="2">
  <nite:pointer href="maptask-landmarks.xml#id(m13_pelicans)" role="landmark"/>
  
    <nite:child href="q8ntb1.wordlist.xml#id(q8ntb1.409)"/>
  
</citation>
<citation id="q8ntb1.cit.427" repetition="2">
  <nite:pointer href="maptask-landmarks.xml#id(m13_crevasse)" role="landmark"/>
  
    <nite:child href="q8ntb1.wordlist.xml#id(q8ntb1.411)"/>
  
</citation>
<citation id="q8ntb1.cit.431" repetition="2">
  <nite:pointer href="maptask-landmarks.xml#id(m0_thatched_mud_hut)" role="landmark"/>
  
    <nite:child href="q8ntb1.wordlist.xml#id(q8ntb1.415)"/>
    <nite:child href="q8ntb1.wordlist.xml#id(q8ntb1.416)"/>
    <nite:child href="q8ntb1.wordlist.xml#id(q8ntb1.417)"/>
  
</citation>
<citation id="q8ntb1.cit.437" repetition="2">
  <nite:pointer href="maptask-landmarks.xml#id(m7_washed_stones)" role="landmark"/>
  
    <nite:child href="q8ntb1.wordlist.xml#id(q8ntb1.421)"/>
    <nite:child href="q8ntb1.wordlist.xml#id(q8ntb1.422)"/>
  
</citation>
<citation id="q8ntb1.cit.442" repetition="2">
  <nite:pointer href="maptask-landmarks.xml#id(m10_rope_bridge)" role="landmark"/>
  <nite:pointer href="maptask-landmarks.xml#id(m13_rope_bridge)" role="landmark"/>
  
    <nite:child href="q8ntb1.wordlist.xml#id(q8ntb1.424)"/>
    <nite:child href="q8ntb1.wordlist.xml#id(q8ntb1.425)"/>
  
</citation>
<citation id="q8ntb1.cit.448" repetition="2">
  <nite:pointer href="maptask-landmarks.xml#id(m10_great_lake)" role="landmark"/>
  
    <nite:child href="q8ntb1.wordlist.xml#id(q8ntb1.427)"/>
    <nite:child href="q8ntb1.wordlist.xml#id(q8ntb1.428)"/>
  
</citation>
<citation id="q8ntb1.cit.453" repetition="2">
  <nite:pointer href="maptask-landmarks.xml#id(m13_slate_mountain)" role="landmark"/>
  
    <nite:child href="q8ntb1.wordlist.xml#id(q8ntb1.432)"/>
    <nite:child href="q8ntb1.wordlist.xml#id(q8ntb1.433)"/>
  
</citation>
<citation id="q8ntb1.cit.458" repetition="2">
  <nite:pointer href="maptask-landmarks.xml#id(m0_west_lake)" role="landmark"/>
  
    <nite:child href="q8ntb1.wordlist.xml#id(q8ntb1.435)"/>
    <nite:child href="q8ntb1.wordlist.xml#id(q8ntb1.436)"/>
  
</citation>
<citation id="q8ntb1.cit.463" repetition="2">
  <nite:pointer href="maptask-landmarks.xml#id(m0_camera_shop)" role="landmark"/>
  
    <nite:child href="q8ntb1.wordlist.xml#id(q8ntb1.440)"/>
    <nite:child href="q8ntb1.wordlist.xml#id(q8ntb1.441)"/>
  
</citation>
<citation id="q8ntb1.cit.468" repetition="2">
  <nite:pointer href="maptask-landmarks.xml#id(m10_gold_mine)" role="landmark"/>
  
    <nite:child href="q8ntb1.wordlist.xml#id(q8ntb1.445)"/>
    <nite:child href="q8ntb1.wordlist.xml#id(q8ntb1.446)"/>
  
</citation>
<citation id="q8ntb1.cit.473" repetition="2">
  <nite:pointer href="maptask-landmarks.xml#id(m13_secret_valley)" role="landmark"/>
  
    <nite:child href="q8ntb1.wordlist.xml#id(q8ntb1.448)"/>
    <nite:child href="q8ntb1.wordlist.xml#id(q8ntb1.449)"/>
  
</citation>
<citation id="q8ntb1.cit.478" repetition="2">
  <nite:pointer href="maptask-landmarks.xml#id(m0_alpine_garden)" role="landmark"/>
  
    <nite:child href="q8ntb1.wordlist.xml#id(q8ntb1.453)"/>
    <nite:child href="q8ntb1.wordlist.xml#id(q8ntb1.454)"/>
  
</citation>
<citation id="q8ntb1.cit.483" repetition="2">
  <nite:pointer href="maptask-landmarks.xml#id(m0_disused_monastery)" role="landmark"/>
  
    <nite:child href="q8ntb1.wordlist.xml#id(q8ntb1.456)"/>
    <nite:child href="q8ntb1.wordlist.xml#id(q8ntb1.457)"/>
  
</citation>
<citation id="q8ntb1.cit.488" repetition="2">
  <nite:pointer href="maptask-landmarks.xml#id(m10_crocodiles)" role="landmark"/>
  
    <nite:child href="q8ntb1.wordlist.xml#id(q8ntb1.459)"/>
  
</citation>
<citation id="q8ntb1.cit.492" repetition="2">
  <nite:pointer href="maptask-landmarks.xml#id(m7_flagship)" role="landmark"/>
  
    <nite:child href="q8ntb1.wordlist.xml#id(q8ntb1.463)"/>
  
</citation>
<citation id="q8ntb1.cit.496" repetition="2">
  <nite:pointer href="maptask-landmarks.xml#id(m10_springboks)" role="landmark"/>
  
    <nite:child href="q8ntb1.wordlist.xml#id(q8ntb1.467)"/>
  
</citation>
<citation id="q8ntb1.cit.500" repetition="2">
  <nite:pointer href="maptask-landmarks.xml#id(m13_submerged_rocks)" role="landmark"/>
  
    <nite:child href="q8ntb1.wordlist.xml#id(q8ntb1.469)"/>
    <nite:child href="q8ntb1.wordlist.xml#id(q8ntb1.470)"/>
  
</citation>
<citation id="q8ntb1.cit.505" repetition="2">
  <nite:pointer href="maptask-landmarks.xml#id(m13_collapsed_shelter)" role="landmark"/>
  
    <nite:child href="q8ntb1.wordlist.xml#id(q8ntb1.472)"/>
    <nite:child href="q8ntb1.wordlist.xml#id(q8ntb1.473)"/>
  
</citation>
</nite:root>

